x11pygrid/__init__.py
x11pygrid/x11pygrid.py
x11pygrid-1.0.2.data/scripts/x11pygrid
x11pygrid-1.0.2.dist-info/METADATA
x11pygrid-1.0.2.dist-info/WHEEL
x11pygrid-1.0.2.dist-info/top_level.txt
x11pygrid-1.0.2.dist-info/RECORD
