Metadata-Version: 2.1
Name: x11pygrid
Version: 1.0.2
Summary: Easily organize your open windows by tiling, resizing and positioning them. It supports multiple monitors!
Home-page: https://pypi.org/project/x11pygrid/
Author: Hilary Jendrasiak
Author-email: sylogista@sylogista.pl
License: UNKNOWN
Project-URL: Documentation, https://github.com/pkkid/pygrid/blob/master/README.md
Project-URL: Bug Reports, https://github.com/pkkid/pygrid/issues
Project-URL: Source Code, https://github.com/pkkid/pygrid
Keywords: X11,tilt,resize
Platform: UNKNOWN
Classifier: Development Status :: 5 - Production/Stable
Classifier: Topic :: Desktop Environment
Classifier: Topic :: Desktop Environment :: Window Managers
Classifier: Topic :: Utilities
Classifier: Intended Audience :: End Users/Desktop
Classifier: Environment :: X11 Applications
Classifier: Operating System :: POSIX
Classifier: Operating System :: POSIX :: BSD :: FreeBSD
Classifier: Operating System :: POSIX :: Linux
Classifier: Programming Language :: Python :: 3
Classifier: Programming Language :: Python :: 3.6
Classifier: Programming Language :: Python :: 3.7
Classifier: Programming Language :: Python :: 3.8
Classifier: Programming Language :: Python :: 3.9
Classifier: Programming Language :: Python :: 3 :: Only
Classifier: License :: OSI Approved :: GNU General Public License v2 (GPLv2)
Requires-Python: >=3.6
Requires-Dist: Xlib
Requires-Dist: single-process
Requires-Dist: PyGObject
